EduNLP/__init__.py
EduNLP/constant.py
EduNLP/main.py
EduNLP/Formula/Formula.py
EduNLP/Formula/__init__.py
EduNLP/Formula/ast/__init__.py
EduNLP/Formula/ast/ast.py
EduNLP/Formula/ast/katex.py
EduNLP/Formula/viz/__init__.py
EduNLP/Formula/viz/m_viz.py
EduNLP/Formula/viz/tree_viz.py
EduNLP/Formula/viz/utils.py
EduNLP/Formula/viz/viz.py
EduNLP/I2V/__init__.py
EduNLP/I2V/i2v.py
EduNLP/ModelZoo/__init__.py
EduNLP/ModelZoo/base_model.py
EduNLP/ModelZoo/bert/__init__.py
EduNLP/ModelZoo/bert/bert.py
EduNLP/ModelZoo/disenqnet/__init__.py
EduNLP/ModelZoo/disenqnet/disenqnet.py
EduNLP/ModelZoo/disenqnet/modules.py
EduNLP/ModelZoo/disenqnet/utils.py
EduNLP/ModelZoo/quesnet/__init__.py
EduNLP/ModelZoo/quesnet/modules.py
EduNLP/ModelZoo/quesnet/quesnet.py
EduNLP/ModelZoo/quesnet/util.py
EduNLP/ModelZoo/rnn/__init__.py
EduNLP/ModelZoo/rnn/harnn.py
EduNLP/ModelZoo/rnn/rnn.py
EduNLP/ModelZoo/utils/__init__.py
EduNLP/ModelZoo/utils/data.py
EduNLP/ModelZoo/utils/device.py
EduNLP/ModelZoo/utils/masker.py
EduNLP/ModelZoo/utils/modules.py
EduNLP/ModelZoo/utils/padder.py
EduNLP/ModelZoo/utils/torch_utils.py
EduNLP/Pipeline/__init__.py
EduNLP/Pipeline/base.py
EduNLP/Pipeline/components.py
EduNLP/Pipeline/knowledge_prediction.py
EduNLP/Pipeline/mappings.py
EduNLP/Pipeline/property_prediction.py
EduNLP/Pretrain/__init__.py
EduNLP/Pretrain/bert_vec.py
EduNLP/Pretrain/disenqnet_vec.py
EduNLP/Pretrain/elmo_vec.py
EduNLP/Pretrain/gensim_vec.py
EduNLP/Pretrain/hugginface_utils.py
EduNLP/Pretrain/pretrian_utils.py
EduNLP/Pretrain/quesnet_vec.py
EduNLP/SIF/__init__.py
EduNLP/SIF/constants.py
EduNLP/SIF/sif.py
EduNLP/SIF/parser/__init__.py
EduNLP/SIF/parser/parser.py
EduNLP/SIF/segment/__init__.py
EduNLP/SIF/segment/segment.py
EduNLP/SIF/tokenization/__init__.py
EduNLP/SIF/tokenization/tokenization.py
EduNLP/SIF/tokenization/formula/__init__.py
EduNLP/SIF/tokenization/formula/ast_token.py
EduNLP/SIF/tokenization/formula/formula.py
EduNLP/SIF/tokenization/formula/linear_token.py
EduNLP-0.0.9.dist-info/AUTHORS.md
EduNLP-0.0.9.dist-info/LICENSE
EduNLP-0.0.9.dist-info/METADATA
EduNLP-0.0.9.dist-info/WHEEL
EduNLP-0.0.9.dist-info/entry_points.txt
EduNLP-0.0.9.dist-info/top_level.txt
EduNLP-0.0.9.dist-info/RECORD
